Verilog/Week 3/mux4.v
module MUX2(input wire a,b,s,output wire y);
assign y = (s==0)?a:b;
endmodule

module MUX4(input wire[3:0] i,input wire s1,s2,output wire y);
wire m,n;
MUX2 m1(i[0],i[1],s1,m);
MUX2 m2(i[2],i[3],s2,n);
MUX2 m3(m,n,s2,y);
endmodule

Verilog/Week 3/testBench2to1.v
module TB;
reg A,B,S;
wire X;
initial
begin
$dumpfile("dump.vcd");
$dumpvars(0,TB);
end
MUX2 mux(.a(A), .b(B), .s(S), .y(X));
initial
begin
S = 1'b0;
A = 1'b0;
B = 1'b0;
#5
A = 1'b0;
B = 1'b1;
#5
A = 1'b1;
B = 1'b0;
#5
A = 1'b1;
B = 1'b1;
#5
S = 1'b0;
A = 1'b0;
B = 1'b0;
#5
A = 1'b0;
B = 1'b1;
#5
A = 1'b1;
B = 1'b0;
#5
A = 1'b1;
B = 1'b1;
end
endmodule

Verilog/Week 3/dump.vcd
$date
	Thu Sep  9 10:03:41 2021
$end
$version
	Icarus Verilog
$end
$timescale
	1s
$end
$scope module TB $end
$var wire 1 ! X $end
$var reg 1 " A $end
$var reg 1 # B $end
$var reg 1 $ S $end
$scope module mux $end
$var wire 1 % a $end
$var wire 1 & b $end
$var wire 1 ' s $end
$var wire 1 ! y $end
$upscope $end
$upscope $end
$enddefinitions $end
#0
$dumpvars
0'
0&
0%
0$
0#
0"
0!
$end
#5
1#
1&
#10
1!
0#
0&
1"
1%
#15
1#
1&
#20
0!
0#
0&
0"
0%
#25
1#
1&
#30
1!
0#
0&
1"
1%
#35
1#
1&
